autodoc_traits.py
autodoc_traits-1.2.2.dist-info/METADATA
autodoc_traits-1.2.2.dist-info/WHEEL
autodoc_traits-1.2.2.dist-info/licenses/LICENSE
autodoc_traits-1.2.2.dist-info/RECORD
