Metadata-Version: 2.3
Name: autodoc-traits
Version: 1.2.2
Summary: Sphinx extension to autodoc traitlets
Project-URL: Documentation, https://github.com/jupyterhub/autodoc-traits#readme
Project-URL: Issues, https://github.com/jupyterhub/autodoc-traits/issues
Project-URL: Source, https://github.com/jupyterhub/autodoc-traits
Author-email: Jupyter Development Team <jupyter@googlegroups.com>
License: BSD 3-Clause License
License-File: LICENSE
Keywords: autodoc,extension,sphinx,traitlets
Classifier: Development Status :: 5 - Production/Stable
Classifier: Operating System :: OS Independent
Classifier: Programming Language :: Python :: 3
Requires-Python: >=3.7
Requires-Dist: sphinx>=4
Requires-Dist: traitlets>=4
Provides-Extra: test
Requires-Dist: pytest; extra == 'test'
